saboteur/application/facade.py
saboteur/domain/mutation/configs.py
saboteur/domain/mutation/contexts.py
saboteur/domain/mutation/strategies.py
saboteur/infrastructure/strategies/flippings.py
saboteur/infrastructure/strategies/injections.py
saboteur/infrastructure/strategies/randomizations.py
saboteur/utils/generic.py
saboteur/utils/logging.py
saboteur/utils/sampling.py
saboteur/utils/types.py
saboteur-0.1.5.dist-info/METADATA
saboteur-0.1.5.dist-info/WHEEL
saboteur-0.1.5.dist-info/licenses/LICENSE
saboteur-0.1.5.dist-info/RECORD
