Metadata-Version: 2.4
Name: saboteur
Version: 0.1.5
Summary: 
License-File: LICENSE
Author: Ryu0n
Author-email: hsung951027@gmail.com
Requires-Python: >=3.13,<4.0
Classifier: Programming Language :: Python :: 3
Classifier: Programming Language :: Python :: 3.13
Classifier: Programming Language :: Python :: 3.14
Requires-Dist: pydantic (>=2.12.5,<3.0.0)
